astropop/__init__.py
astropop/_unit_property.py
astropop/file_collection.py
astropop/fits_utils.py
astropop/flags.py
astropop/logger.py
astropop/py_utils.py
astropop/testing.py
astropop/version.py
astropop/astrometry/__init__.py
astropop/astrometry/astrometrynet.py
astropop/astrometry/coords_utils.py
astropop/astrometry/manual_wcs.py
astropop/catalogs/__init__.py
astropop/catalogs/_online_tools.py
astropop/catalogs/_sources_catalog.py
astropop/catalogs/gaia.py
astropop/catalogs/simbad.py
astropop/catalogs/vizier.py
astropop/catalogs/vizier_catalogs/allwise.yml
astropop/catalogs/vizier_catalogs/apass9.yml
astropop/catalogs/vizier_catalogs/denis.yml
astropop/catalogs/vizier_catalogs/gsc242.yml
astropop/catalogs/vizier_catalogs/hip.yml
astropop/catalogs/vizier_catalogs/twomass.yml
astropop/catalogs/vizier_catalogs/tycho2.yml
astropop/catalogs/vizier_catalogs/ucac4.yml
astropop/catalogs/vizier_catalogs/ucac5.yml
astropop/catalogs/vizier_catalogs/vsx.yml
astropop/catalogs/vizier_catalogs/wise.yml
astropop/framedata/__init__.py
astropop/framedata/_compat.py
astropop/framedata/_memmap.py
astropop/framedata/cache_manager.py
astropop/framedata/framedata.py
astropop/framedata/util.py
astropop/image/__init__.py
astropop/image/_tools.py
astropop/image/imarith.py
astropop/image/imcombine.py
astropop/image/processing.py
astropop/image/register.py
astropop/math/__init__.py
astropop/math/_deriv.py
astropop/math/array.py
astropop/math/hasher.py
astropop/math/models.py
astropop/math/physical.py
astropop/photometry/__init__.py
astropop/photometry/aperture.py
astropop/photometry/background.py
astropop/photometry/detection.py
astropop/polarimetry/__init__.py
astropop-0.9.4.dist-info/METADATA
astropop-0.9.4.dist-info/WHEEL
astropop-0.9.4.dist-info/top_level.txt
astropop-0.9.4.dist-info/RECORD
