Metadata-Version: 2.1
Name: astropop
Version: 0.9.4
Summary: Astronomical Polarimetry and Photometry Pipeline
Author-email: Julio Campagnolo <julio.campagnolo@cefet-rj.br>
License: BSD-3-Clause
Project-URL: homepage, https://github.com/sparc4-dev/astropop
Project-URL: documentation, https://astropop.readthedocs.io/en/latest/
Project-URL: repository, https://github.com/sparc4-dev/astropop
Keywords: astronomy,astrophysics,science,units,data-reduction,photometry,polarimetry,astrometry
Classifier: Intended Audience :: Science/Research
Classifier: License :: OSI Approved :: BSD License
Classifier: Operating System :: OS Independent
Classifier: Programming Language :: C
Classifier: Programming Language :: Cython
Classifier: Programming Language :: Python :: 3
Classifier: Programming Language :: Python :: Implementation :: CPython
Classifier: Topic :: Scientific/Engineering :: Astronomy
Classifier: Topic :: Scientific/Engineering :: Physics
Requires-Python: >=3.8
Requires-Dist: astropy >=4.3
Requires-Dist: numpy >=1.17
Requires-Dist: scipy >=1.6
Requires-Dist: astroquery
Requires-Dist: scikit-image
Requires-Dist: scikit-learn
Requires-Dist: photutils >=1.7
Requires-Dist: pytz
Requires-Dist: pyyaml
Requires-Dist: astroscrappy
Requires-Dist: astroalign
Requires-Dist: tqdm
Requires-Dist: nest-asyncio
Requires-Dist: dbastable
Requires-Dist: platformdirs
Provides-Extra: all
Requires-Dist: matplotlib ; extra == 'all'
Provides-Extra: docs
Requires-Dist: ipython ; extra == 'docs'
Requires-Dist: ipykernel ; extra == 'docs'
Requires-Dist: sphinx ; extra == 'docs'
Requires-Dist: sphinx-astropy ; extra == 'docs'
Requires-Dist: sphinx-book-theme ; extra == 'docs'
Requires-Dist: numpydoc ; extra == 'docs'
Requires-Dist: nbsphinx ; extra == 'docs'
Requires-Dist: pandoc ; extra == 'docs'
Provides-Extra: test
Requires-Dist: pytest-astropy ; extra == 'test'
Requires-Dist: pytest-remotedata ; extra == 'test'
Requires-Dist: testfixtures ; extra == 'test'
Requires-Dist: pytest-rerunfailures ; extra == 'test'
